pysparkplug/__init__.py
pysparkplug/_client.py
pysparkplug/_config.py
pysparkplug/_constants.py
pysparkplug/_datatype.py
pysparkplug/_edge_node.py
pysparkplug/_enums.py
pysparkplug/_error.py
pysparkplug/_message.py
pysparkplug/_metric.py
pysparkplug/_payload.py
pysparkplug/_strenum.py
pysparkplug/_time.py
pysparkplug/_topic.py
pysparkplug/_types.py
pysparkplug/_version.py
pysparkplug/py.typed
pysparkplug/_protobuf/__init__.py
pysparkplug/_protobuf/sparkplug_b_pb2.py
pysparkplug-0.5.0.dist-info/METADATA
pysparkplug-0.5.0.dist-info/WHEEL
pysparkplug-0.5.0.dist-info/licenses/LICENSE
pysparkplug-0.5.0.dist-info/RECORD
