Metadata-Version: 2.4
Name: pysparkplug
Version: 0.5.0
Summary: An open-source, Python implementation of Sparkplug B, an MQTT topic and payload definition standard
Project-URL: Documentation, https://pysparkplug.mattefay.com
Project-URL: Changelog, https://pysparkplug.mattefay.com/en/stable/changelog.html
Project-URL: Source, https://github.com/matteosox/pysparkplug
Project-URL: Bug Report, https://github.com/matteosox/pysparkplug/issues/new/choose
Project-URL: Feature Request, https://github.com/matteosox/pysparkplug/issues/new/choose
Author-email: Matt Fay <matt.e.fay@gmail.com>
License: Apache License, Version 2.0
License-File: LICENSE
Keywords: automation,manufacturing,mqtt,sparkplug
Classifier: Development Status :: 2 - Pre-Alpha
Classifier: Intended Audience :: Manufacturing
Classifier: License :: OSI Approved :: Apache Software License
Classifier: Natural Language :: English
Classifier: Operating System :: OS Independent
Classifier: Programming Language :: Python
Classifier: Programming Language :: Python :: 3
Classifier: Programming Language :: Python :: 3 :: Only
Classifier: Programming Language :: Python :: 3.9
Classifier: Programming Language :: Python :: 3.10
Classifier: Programming Language :: Python :: 3.11
Classifier: Programming Language :: Python :: 3.12
Classifier: Programming Language :: Python :: 3.13
Classifier: Programming Language :: Python :: Implementation :: CPython
Classifier: Typing :: Typed
Requires-Python: >=3.9
Requires-Dist: paho-mqtt<2
Requires-Dist: protobuf>=5.28.2
Requires-Dist: typing-extensions>=4.12.2; python_full_version < '3.11'
